<?xml version = '1.0' encoding = 'UTF-8'?>
<Relation class="oracle.dbtools.crest.model.design.logical.Relation" name="Reciclador_Censo_FK" directorySegmentName="seg_0" id="CDE9D6E8-0AD3-E4ED-DD9F-39FE5B65775A">
<createdBy>Edelberto</createdBy>
<createdTime>2022-11-09 22:11:01 UTC</createdTime>
<generatorID>6864D844-ABBF-D39D-FD9D-2B67228441F7</generatorID>
<ownerDesignName>recicladores modelo</ownerDesignName>
<engineerTo>
<item key="05EF2D2C-FE3A-A466-B6EB-3E2F8D7C3F32" value="true"/>
<item key="6664BC7E-F11C-6F80-411A-BB2E665BFCC5" value="true"/>
</engineerTo>
<sourcePk>8AFB08EB-066B-415C-1BEA-3F41132595CB</sourcePk>
<identifying>false</identifying>
<optionalSource>true</optionalSource>
<optionalTarget>false</optionalTarget>
<sourceCardinality>1</sourceCardinality>
<sourceEntity>90C895E7-47B4-E720-2843-D2A0F8BE0A40</sourceEntity>
<targetCardinalityString>*</targetCardinalityString>
<targetEntity>0041856F-B474-495D-00C7-6FF0620053AE</targetEntity>
<transferable>true</transferable>
<deleteRule>NO ACTION</deleteRule>
</Relation>